bin/__init__.py
nlp_segmentation/__init__.py
nlp_segmentation-1.2.7.data/scripts/baidu_fenci
nlp_segmentation-1.2.7.data/scripts/sougou_fenci
nlp_segmentation-1.2.7.dist-info/DESCRIPTION.rst
nlp_segmentation-1.2.7.dist-info/METADATA
nlp_segmentation-1.2.7.dist-info/RECORD
nlp_segmentation-1.2.7.dist-info/WHEEL
nlp_segmentation-1.2.7.dist-info/metadata.json
nlp_segmentation-1.2.7.dist-info/top_level.txt
