Metadata-Version: 2.0
Name: nlp-segmentation
Version: 1.2.7
Summary: 分词工具
Home-page: https://github.com/SharpCX/nlp_segmentation.git
Author: cx
Author-email: sharpcx@live.com
License: UNKNOWN
Platform: UNKNOWN
Classifier: Programming Language :: Python :: 3
Classifier: License :: OSI Approved :: MIT License
Classifier: Operating System :: OS Independent
Requires-Dist: requests
